MANIFEST.in
README.md
setup.py
runflare/.runflare_ignore
runflare/__init__.py
runflare/exceptions.py
runflare/gitignore_parser.py
runflare/runflare.py
runflare/settings.py
runflare/utils.py
runflare/version_check.py
runflare.egg-info/PKG-INFO
runflare.egg-info/SOURCES.txt
runflare.egg-info/dependency_links.txt
runflare.egg-info/entry_points.txt
runflare.egg-info/requires.txt
runflare.egg-info/top_level.txt
runflare/inquirer/__init__.py
runflare/inquirer/errors.py
runflare/inquirer/events.py
runflare/inquirer/prompt.py
runflare/inquirer/questions.py
runflare/inquirer/shortcuts.py
runflare/inquirer/themes.py
runflare/inquirer/render/__init__.py
runflare/inquirer/render/console/__init__.py
runflare/inquirer/render/console/_checkbox.py
runflare/inquirer/render/console/_confirm.py
runflare/inquirer/render/console/_editor.py
runflare/inquirer/render/console/_list.py
runflare/inquirer/render/console/_password.py
runflare/inquirer/render/console/_path.py
runflare/inquirer/render/console/_text.py
runflare/inquirer/render/console/base.py
runflare/runflare_client/__init__.py
runflare/runflare_client/custom_pathlib.py
runflare/runflare_client/requester.py
runflare/runflare_client/web_socket.py
runflare/runflare_client/account/__init__.py
runflare/runflare_client/account/auth.py
runflare/runflare_client/analyze/__init__.py
runflare/runflare_client/analyze/events.py
runflare/runflare_client/analyze/log.py
runflare/runflare_client/data_manager/__init__.py
runflare/runflare_client/data_manager/adapter.py
runflare/runflare_client/data_manager/base_manager.py
runflare/runflare_client/data_manager/sqlite_manager.py
runflare/runflare_client/deploy/__init__.py
runflare/runflare_client/deploy/cache.py
runflare/runflare_client/deploy/deployment.py
runflare/runflare_client/deploy/upload.py
runflare/runflare_client/service/__init__.py
runflare/runflare_client/service/manage.py
runflare/runflare_client/service/projects.py