Metadata-Version: 2.1
Name: runflare
Version: 1.1.6
Summary: Official CLI for runflare PaaS
Home-page: https://github.com/parswebserver/runflare-cli
Author: RUNFLARE DEVELOPMENT TEAM
Author-email: parswebserver@gmail.com
License: UNKNOWN
Keywords: PaaS,runflare,Kubernetes
Platform: UNKNOWN
Classifier: Development Status :: 5 - Production/Stable
Classifier: Topic :: Utilities
